{
    "telegram": {
        "bot_token": "YOUR_BOT_TOKEN_HERE",
        "chat_id": "YOUR_CHAT_ID_HERE",
        "enabled": true
    },
    "strategy": {
        "hold_days": 5,
        "stop_loss_pct": -7.0,
        "top_n": 2,
        "max_positions": 2,
        "min_prob": 0.50,
        "max_prob": 0.85,
        "cost_bps": 10,
        "skip_wednesday": false,
        "big_move_threshold": 5.0,
        "training_lookback_days": 504,
        "retrain_every_days": 63
    },
    "schedule": {
        "scan_time_utc": "21:30",
        "timezone": "US/Eastern",
        "scan_days": "mon-fri"
    },
    "paper_trading": {
        "start_capital": 100000,
        "track_results": true
    },
    "alpaca": {
        "enabled": false,
        "api_key": "YOUR_ALPACA_API_KEY",
        "api_secret": "YOUR_ALPACA_API_SECRET",
        "base_url": "https://paper-api.alpaca.markets"
    },
    "lepotato": {
        "ip": "YOUR_LEPOTATO_IP",
        "project_dir": "/root/stock-scanner"
    }
}
